sociolitics/__init__.py
sociolitics/dar.py
sociolitics/filters.py
sociolitics/lemmatizer.py
sociolitics/main.py
sociolitics/support.py
sociolitics/visualization.py
sociolitics/visualization_plotly.py
sociolitics/wordembedders.py
sociolitics-0.1.5.dist-info/LICENSE
sociolitics-0.1.5.dist-info/METADATA
sociolitics-0.1.5.dist-info/WHEEL
sociolitics-0.1.5.dist-info/top_level.txt
sociolitics-0.1.5.dist-info/RECORD
